arcade_obsidian/__init__.py
arcade_obsidian/constants.py
arcade_obsidian/index/__init__.py
arcade_obsidian/index/background.py
arcade_obsidian/index/index.py
arcade_obsidian/index/parse.py
arcade_obsidian/start.py
arcade_obsidian/tools/__init__.py
arcade_obsidian/tools/read.py
arcade_obsidian/tools/search.py
arcade_obsidian/tools/write.py
arcade_obsidian-0.2.1.dist-info/LICENSE
arcade_obsidian-0.2.1.dist-info/METADATA
arcade_obsidian-0.2.1.dist-info/WHEEL
arcade_obsidian-0.2.1.dist-info/RECORD
