Metadata-Version: 2.1
Name: arcade_obsidian
Version: 0.2.1
Summary: Arcade tools for using LLMs to interact with obsidian markdown notes
Author: spartee
Author-email: sam@partee.io
Requires-Python: >=3.10,<4.0
Classifier: Programming Language :: Python :: 3
Classifier: Programming Language :: Python :: 3.10
Classifier: Programming Language :: Python :: 3.11
Classifier: Programming Language :: Python :: 3.12
Classifier: Programming Language :: Python :: 3.13
Requires-Dist: Whoosh (>=2.7.4,<3.0.0)
Requires-Dist: aiofiles (>=24.1.0,<25.0.0)
Requires-Dist: arcade-ai (==1.0.*)
